odoo/addons/sale_coupon_limit/README.rst
odoo/addons/sale_coupon_limit/__init__.py
odoo/addons/sale_coupon_limit/__manifest__.py
odoo/addons/sale_coupon_limit/i18n/it.po
odoo/addons/sale_coupon_limit/i18n/sale_coupon_limit.pot
odoo/addons/sale_coupon_limit/models/__init__.py
odoo/addons/sale_coupon_limit/models/coupon_coupon.py
odoo/addons/sale_coupon_limit/models/coupon_program.py
odoo/addons/sale_coupon_limit/models/coupon_rule.py
odoo/addons/sale_coupon_limit/readme/CONFIGURE.rst
odoo/addons/sale_coupon_limit/readme/CONTRIBUTORS.rst
odoo/addons/sale_coupon_limit/readme/DESCRIPTION.rst
odoo/addons/sale_coupon_limit/readme/USAGE.rst
odoo/addons/sale_coupon_limit/security/ir.model.access.csv
odoo/addons/sale_coupon_limit/static/description/icon.png
odoo/addons/sale_coupon_limit/static/description/icon.svg
odoo/addons/sale_coupon_limit/static/description/index.html
odoo/addons/sale_coupon_limit/tests/__init__.py
odoo/addons/sale_coupon_limit/tests/test_sale_coupon_limit.py
odoo14_addon_sale_coupon_limit-14.0.1.0.1.dev6.dist-info/METADATA
odoo14_addon_sale_coupon_limit-14.0.1.0.1.dev6.dist-info/WHEEL
odoo14_addon_sale_coupon_limit-14.0.1.0.1.dev6.dist-info/top_level.txt
odoo14_addon_sale_coupon_limit-14.0.1.0.1.dev6.dist-info/RECORD
