Metadata-Version: 2.1
Name: odoo14-addon-sale-coupon-limit
Version: 14.0.1.0.1.dev6
Summary: Restrict number of promotions per customer or salesman
Home-page: https://github.com/OCA/sale-promotion
Author: Tecnativa, Odoo Community Association (OCA)
Author-email: support@odoo-community.org
License: AGPL-3
Platform: UNKNOWN
Classifier: Programming Language :: Python
Classifier: Framework :: Odoo
Classifier: Framework :: Odoo :: 14.0
Classifier: License :: OSI Approved :: GNU Affero General Public License v3
Classifier: Development Status :: 4 - Beta
Requires-Python: >=3.6
Requires-Dist: odoo14-addon-coupon-limit
Requires-Dist: odoo14-addon-sale-commercial-partner
Requires-Dist: odoo14-addon-sale-coupon-order-line-link
Requires-Dist: odoo <14.1dev,>=14.0a
